<?xml version="1.0" encoding="UTF-8" ?>
<odoo>

    <record id="ss_erp_ifdb_youki_kensa_view_search" model="ir.ui.view">
        <field name="name">ss_erp.ifdb.youki.kensa.view.search</field>
        <field name="model">ss_erp.ifdb.youkikensa.billing.file.header</field>
        <field name="arch" type="xml">
            <search string="Youki kensa">
                <field name="upload_date"/>
                <field name="name"
                       filter_domain="[('name', 'ilike', self)]"/>
                <group string="Group By">
                    <filter name="flt_status" string="Status" context="{'group_by': 'status'}"/>
                    <filter name="flt_branch" string="Branch" context="{'group_by': 'branch_id'}"/>
                    <filter name="flt_user" string="User" context="{'group_by': 'user_id'}"/>
                </group>
            </search>
        </field>
    </record>

    <record id="ss_erp_ss_erp_ifdb_youki_kensa_tree" model="ir.ui.view">
        <field name="name">ss_erp.ifdb.youki.kensa.view.tree</field>
        <field name="model">ss_erp.ifdb.youkikensa.billing.file.header</field>
        <field name="arch" type="xml">
            <tree string="容器管理システムファイル取込">
                <field name="upload_date"/>
                <field name="name"/>
                <field name="branch_id"/>
                <field name="user_id"/>
                <field name="status"
                       widget="badge"
                       decoration-info="status=='success'"
                       decoration-warning="status=='wait'"
                       decoration-danger="status=='error'"/>
            </tree>
        </field>
    </record>

    <record id="ss_erp_ifdb_youki_kensa_view_form" model="ir.ui.view">
        <field name="name">ss_erp.ifdb.youki.kensa.view.form</field>
        <field name="model">ss_erp.ifdb.youkikensa.billing.file.header</field>
        <field name="arch" type="xml">
            <form string="容器検査所ファイル取込">
                <header>
                    <field name="has_data_import" invisible="1"/>
                    <button type="object" attrs="{'invisible' : [('has_data_import', '=', True)]}"
                            name="action_import"
                            string="アップロード"
                            class="oe_highlight"/>
                    <button type="object"
                            name="action_processing_execution"
                            string="処理実行"
                            class="oe_highlight"/>
                </header>
                <sheet>
                    <group>
                        <group>
                            <field name="name" required="1"/>
                            <field name="upload_date" required="1"/>
                            <field name="status" readonly="1"/>
                        </group>
                        <group>
                            <field name="user_id" required="1" options="{'no_create_edit': True}"/>
                            <field name="branch_id" required="1" options="{'no_create_edit': True}"/>
                        </group>
                    </group>
                    <notebook>
                        <page name="data_records" string="データレコード">
                            <field name="youki_kensa_detail_ids">
                                <tree editable="bottom">
                                    <field name="status"
                                           widget="badge"
                                           decoration-info="status=='success'"
                                           decoration-warning="status=='wait'"
                                           decoration-danger="status=='error'"/>
                                    <field name="processing_date" readonly="True"/>
                                    <field name="sales_date" readonly="True"/>
                                    <field name="slip_no" readonly="True"/>
                                    <field name="field_3" readonly="True"/>
                                    <field name="billing_abbreviation" readonly="True"/>
                                    <field name="billing_code" readonly="True"/>
                                    <field name="customer_code" readonly="True"/>
                                    <field name="customer_abbreviation" readonly="True"/>
                                    <field name="product_code" readonly="True"/>
                                    <field name="product_name" readonly="True"/>
                                    <field name="unit_price" readonly="True"/>
                                    <field name="return_quantity_for_sale" readonly="True"/>
                                    <field name="net_sales_excluding_tax" readonly="True"/>
                                    <field name="consumption_tax" readonly="True"/>
                                    <field name="remarks" readonly="True"/>
                                    <field name="unit_cost" readonly="True"/>
                                    <field name="description" readonly="True"/>
                                    <field name="error_message" readonly="True"/>
                                    <field name="purchase_id" readonly="True"/>
                                </tree>
                            </field>
                        </page>
                    </notebook>
                </sheet>
                <div class="oe_chatter">
                    <field name="message_follower_ids"/>
                    <field name="activity_ids"/>
                    <field name="message_ids"/>
                </div>
            </form>
        </field>
    </record>

    <record id="ss_erp_ifdb_youki_kensa_action" model="ir.actions.act_window">
        <field name="name">容器検査所ファイル取込</field>
        <field name="res_model">ss_erp.ifdb.youkikensa.billing.file.header</field>
        <field name="view_mode">tree,form</field>
    </record>


    <!-- youki kensa detail view-->
    <record id="ss_erp_ifdb_youki_kensa_detail_view_search" model="ir.ui.view">
        <field name="name">ss_erp.ifdb.youkikensa.billing.file.detail</field>
        <field name="model">ss_erp.ifdb.youkikensa.billing.file.detail</field>
        <field name="arch" type="xml">
            <search string="容器検査所ファイル取込">
                <field name="processing_date"/>
                <filter name="flr_error_status" string="ラーあ" domain="[('status', '=', 'error')]"/>
                <filter name="flr_wait_status" string="処理待ち" domain="[('status', '=', 'wait')]"/>
                <filter name="flr_success_status" string="成功" domain="[('status', '=', 'success')]"/>
                <group string="Group By" expand="0">
                    <filter name="grp_sale_id" string="処理日時" context="{'group_by': 'sales_date'}"/>
                </group>
            </search>
        </field>
    </record>

    <record id="ss_erp_ifdb_youki_kensa_detail_view_tree" model="ir.ui.view">
        <field name="name">ss_erp.ifdb.youki.kensa.detail.view.tree</field>
        <field name="model">ss_erp.ifdb.youkikensa.billing.file.detail</field>
        <field name="arch" type="xml">
            <tree string="容器管理システムデータ" js_class="import_detail_tree">
                <field name="status"
                       widget="badge"
                       decoration-info="status=='success'"
                       decoration-warning="status=='wait'"
                       decoration-danger="status=='error'"/>
                <field name="processing_date" readonly="True"/>
                <field name="sales_date" readonly="True"/>
                <field name="slip_no" readonly="True"/>
                <field name="field_3" readonly="True"/>
                <field name="billing_abbreviation" readonly="True"/>
                <field name="billing_code" readonly="True"/>
                <field name="customer_code" readonly="True"/>
                <field name="customer_abbreviation" readonly="True"/>
                <field name="product_code" readonly="True"/>
                <field name="product_name" readonly="True"/>
                <field name="unit_price" readonly="True"/>
                <field name="return_quantity_for_sale" readonly="True"/>
                <field name="net_sales_excluding_tax" readonly="True"/>
                <field name="consumption_tax" readonly="True"/>
                <field name="remarks" readonly="True"/>
                <field name="unit_cost" readonly="True"/>
                <field name="description" readonly="True"/>
                <field name="error_message" readonly="True"/>
                <field name="purchase_id" readonly="True"/>
            </tree>
        </field>
    </record>

    <record id="ss_erp_ifdb_youki_kensa_detail_action" model="ir.actions.act_window">
        <field name="name">容器検査所ファイル取込データ</field>
        <field name="res_model">ss_erp.ifdb.youkikensa.billing.file.detail</field>
        <field name="view_mode">tree</field>
    </record>


</odoo>
